{
	"configurations" : 
	[
		{
			"directories" : 
			[
				{
					"build" : ".",
					"hasInstallRule" : true,
					"jsonFile" : "directory-.-Debug-a41c6e550efcccd73f05.json",
					"minimumCMakeVersion" : 
					{
						"string" : "3.16"
					},
					"projectIndex" : 0,
					"source" : ".",
					"targetIndexes" : 
					[
						0,
						1,
						2
					]
				}
			],
			"name" : "Debug",
			"projects" : 
			[
				{
					"directoryIndexes" : 
					[
						0
					],
					"name" : "PersonalOrganizer",
					"targetIndexes" : 
					[
						0,
						1,
						2
					]
				}
			],
			"targets" : 
			[
				{
					"directoryIndex" : 0,
					"id" : "PersonalOrganizer::@6890427a1f51a3e7e1df",
					"jsonFile" : "target-PersonalOrganizer-Debug-07c5ee281b810714c823.json",
					"name" : "PersonalOrganizer",
					"projectIndex" : 0
				},
				{
					"directoryIndex" : 0,
					"id" : "PersonalOrganizer_autogen::@6890427a1f51a3e7e1df",
					"jsonFile" : "target-PersonalOrganizer_autogen-Debug-fe12f54bc29da58c59b5.json",
					"name" : "PersonalOrganizer_autogen",
					"projectIndex" : 0
				},
				{
					"directoryIndex" : 0,
					"id" : "PersonalOrganizer_autogen_timestamp_deps::@6890427a1f51a3e7e1df",
					"jsonFile" : "target-PersonalOrganizer_autogen_timestamp_deps-Debug-99854df0dcea383ddc9f.json",
					"name" : "PersonalOrganizer_autogen_timestamp_deps",
					"projectIndex" : 0
				}
			]
		}
	],
	"kind" : "codemodel",
	"paths" : 
	{
		"build" : "C:/Users/Admin/Documents/PersonalOrganizer/build/Desktop_Qt_6_8_2_MinGW_64_bit-Debug",
		"source" : "C:/Users/Admin/Documents/PersonalOrganizer"
	},
	"version" : 
	{
		"major" : 2,
		"minor" : 7
	}
}
